{"adult":false,"backdrop_path":null,"belongs_to_collection":null,"budget":0,"genres":[{"id":80,"name":"Crime"},{"id":10749,"name":"Romance"},{"id":18,"name":"Drama"}],"homepage":"","id":10810,"imdb_id":"tt0382271","original_language":"es","original_title":"Rosario Tijeras","overview":"Rosario Tijeras has been abused by men all her life, initially by her stepfather. Years later, she works as a paid assassin, seducing men and killing them when they least expect it. She meets Emilio, a wealthy womanizer, and his best friend, Antonio, at a nightclub, and starts an affair with Emilio despite Antonio's growing feelings for her. But circumstances bring her closer to Antonio, until her past catches up with her in a devastating way.","popularity":3.606,"poster_path":"/xzNN3SZgixfZsAPQ3phh0y8PPQj.jpg","production_companies":[{"id":302,"logo_path":null,"name":"Ibermedia","origin_country":""},{"id":4290,"logo_path":"/ocUWrkAx1627h3WeUENn17dAgOs.png","name":"Moonshot Pictures","origin_country":"BR"},{"id":10630,"logo_path":null,"name":"Rio Negro","origin_country":""},{"id":15878,"logo_path":null,"name":"Fondo de Inversión y Estímulos al Cine (FIDECINE)","origin_country":""},{"id":36920,"logo_path":null,"name":"Maestranza Films","origin_country":""},{"id":77305,"logo_path":null,"name":"Dulce Compania","origin_country":""}],"production_countries":[{"iso_3166_1":"BR","name":"Brazil"},{"iso_3166_1":"CO","name":"Colombia"},{"iso_3166_1":"MX","name":"Mexico"},{"iso_3166_1":"ES","name":"Spain"}],"release_date":"2005-08-12","revenue":0,"runtime":126,"spoken_languages":[{"iso_639_1":"es","name":"Español"}],"status":"Released","tagline":"","title":"Rosario Tijeras","video":false,"vote_average":6.0,"vote_count":31}