{"adult":false,"backdrop_path":null,"belongs_to_collection":null,"budget":0,"genres":[{"id":99,"name":"Documentary"}],"homepage":null,"id":11261,"imdb_id":"","original_language":"en","original_title":"Tutmosis","overview":"No overview found.","popularity":0.6,"poster_path":null,"production_companies":[],"production_countries":[],"release_date":"2006-03-01","revenue":0,"runtime":11,"spoken_languages":[{"iso_639_1":"de","name":"Deutsch"}],"status":"Released","tagline":"","title":"Tutmosis","video":false,"vote_average":0.0,"vote_count":0}