{"adult":false,"backdrop_path":"/xNjtgBLiSyS9mlQRTjNX7b9Zkx7.jpg","belongs_to_collection":null,"budget":10000000,"genres":[{"id":27,"name":"Horror"},{"id":53,"name":"Thriller"}],"homepage":"","id":10359,"imdb_id":"tt0142804","original_language":"en","original_title":"Resurrection","overview":"A seasoned police detective and his partner have just uncovered a string of unusual murders that lead them to a serial killer, who believes that he is the descendant of Judas.","popularity":8.57,"poster_path":"/2j6cMHN1Mx1u8S897VVhO7wSrce.jpg","production_companies":[{"id":3890,"logo_path":null,"name":"Baldwin/Cohen Productions","origin_country":""},{"id":2016,"logo_path":null,"name":"Interlight","origin_country":""}],"production_countries":[{"iso_3166_1":"US","name":"United States of America"}],"release_date":"1999-06-05","revenue":0,"runtime":103,"spoken_languages":[{"iso_639_1":"fr","name":"Français"},{"iso_639_1":"en","name":"English"}],"status":"Released","tagline":"","title":"Resurrection","video":false,"vote_average":6.2,"vote_count":108}