{"adult":false,"backdrop_path":"/kyEL1ilsJ0kPse0A5GVUYZ8U1Ww.jpg","belongs_to_collection":null,"budget":22000000,"genres":[{"id":18,"name":"Drama"},{"id":10749,"name":"Romance"}],"homepage":"","id":10696,"imdb_id":"tt0118589","original_language":"en","original_title":"Glitter","overview":"A young woman is catapulted into pop stardom, with her already-famous DJ boyfriend calling the shots.","popularity":10.311,"poster_path":"/snrZMoZ9Mw6gCZlNmP8WYP7YNCR.jpg","production_companies":[{"id":89627,"logo_path":null,"name":"Glitter Productions","origin_country":""},{"id":89628,"logo_path":null,"name":"Maroon Entertainment","origin_country":""},{"id":415,"logo_path":null,"name":"Laurence Mark Productions","origin_country":"US"},{"id":5,"logo_path":"/71BqEFAF4V3qjjMPCpLuyJFB9A.png","name":"Columbia Pictures","origin_country":"US"},{"id":25,"logo_path":"/qZCc1lty5FzX30aOCVRBLzaVmcp.png","name":"20th Century Fox","origin_country":"US"}],"production_countries":[{"iso_3166_1":"US","name":"United States of America"}],"release_date":"2001-09-21","revenue":5271666,"runtime":104,"spoken_languages":[{"iso_639_1":"en","name":"English"}],"status":"Released","tagline":"In music she found her dream, her love, herself.","title":"Glitter","video":false,"vote_average":3.7,"vote_count":74}