{"adult":false,"backdrop_path":"/rGahtD2ZHff7EdIPk55Q9ED3sCg.jpg","belongs_to_collection":null,"budget":30000000,"genres":[{"id":18,"name":"Drama"},{"id":10749,"name":"Romance"}],"homepage":"","id":10922,"imdb_id":"tt0308383","original_language":"en","original_title":"The Human Stain","overview":"Coleman Silk is a worldly and admired professor who loses his job after unwittingly making a racial slur. To clear his name, Silk writes a book about the events with his friend and colleague Nathan Zuckerman, who in the process discovers a dark secret Silk has hidden his whole life. All the while, Silk engages in an affair with Faunia Farley, a younger woman whose tormented past threatens to unravel the layers of deception Silk has constructed.","popularity":9.388,"poster_path":"/kBHLlbBEKLXlZFHG5y6aveGUwXy.jpg","production_companies":[{"id":53899,"logo_path":null,"name":"Cinepsilon","origin_country":""},{"id":14,"logo_path":"/m6AHu84oZQxvq7n1rsvMNJIAsMu.png","name":"Miramax","origin_country":"US"},{"id":126,"logo_path":"/kADPanRDkKTxncPXXVahvHPUvCj.png","name":"Lakeshore Entertainment","origin_country":"US"},{"id":995,"logo_path":null,"name":"Cinerenta Medienbeteiligungs KG","origin_country":"DE"},{"id":7420,"logo_path":null,"name":"Stone Village Pictures","origin_country":""}],"production_countries":[{"iso_3166_1":"FR","name":"France"},{"iso_3166_1":"DE","name":"Germany"},{"iso_3166_1":"US","name":"United States of America"}],"release_date":"2003-10-29","revenue":0,"runtime":106,"spoken_languages":[{"iso_639_1":"en","name":"English"}],"status":"Released","tagline":"How far would you go to escape the past?","title":"The Human Stain","video":false,"vote_average":6.0,"vote_count":253}