{"adult":false,"backdrop_path":null,"belongs_to_collection":null,"budget":0,"genres":[{"id":18,"name":"Drama"}],"homepage":"","id":1608,"imdb_id":"tt0114917","original_language":"en","original_title":"When Saturday Comes","overview":"Jimmy Muir comes from a typical gritty, northern town where there are only two options: working down the pit or in a factory. But Jimmy has other ideas - he dreams of becoming a professional footballer. Confronted by a bitter and unsupportive father, hard drinking friends and a lifetime of bad habits...has Jimmy the will to achieve his ultimate goal?","popularity":3.02,"poster_path":"/wCMxsLuOZpi7mXWn7NLuNePh2Pe.jpg","production_companies":[{"id":1213,"logo_path":null,"name":"Pint O'Bitter Productions","origin_country":""},{"id":1214,"logo_path":null,"name":"Guild","origin_country":""}],"production_countries":[{"iso_3166_1":"GB","name":"United Kingdom"}],"release_date":"1996-03-01","revenue":0,"runtime":95,"spoken_languages":[{"iso_639_1":"en","name":"English"}],"status":"Released","tagline":"To Jimmy Life Was Just A Game...Until The Game Became His Life!","title":"When Saturday Comes","video":false,"vote_average":5.8,"vote_count":16}