{"adult":false,"backdrop_path":"/o3bSYbap4gDnHeAru7umPVWTzAP.jpg","belongs_to_collection":{"id":105764,"name":"The Tall Blond Man Collection","poster_path":"/nvikKNcoe8WeFE5U5Qgi6lVygmw.jpg","backdrop_path":"/ttjbXNCNz7Bm9YdLVhXGXBJdy4j.jpg"},"budget":0,"genres":[{"id":35,"name":"Comedy"}],"homepage":"","id":10939,"imdb_id":"tt0072080","original_language":"fr","original_title":"Le retour du grand blond","overview":"With 'little captain' Cambrai raising serious doubts about the reality of the so-called \"super spy\", Colonel Toulouse kidnaps Christine and forces Francois to play again the character of \"The Tall Blond Man with One Black Shoe\" in some fake adventures. All this to stop the investigation into the death of Colonel Milan.","popularity":6.59,"poster_path":"/5ABNUdtWf7oU6cwOpNq46zhQ1fS.jpg","production_companies":[{"id":9,"logo_path":"/nda3dTUYdDrJ6rZqBpYvY865aDv.png","name":"Gaumont","origin_country":"FR"}],"production_countries":[{"iso_3166_1":"FR","name":"France"}],"release_date":"1974-11-12","revenue":0,"runtime":81,"spoken_languages":[{"iso_639_1":"fr","name":"Français"}],"status":"Released","tagline":"","title":"The Return of the Tall Blond Man with One Black Shoe","video":false,"vote_average":6.6,"vote_count":110}