{"adult":false,"backdrop_path":null,"belongs_to_collection":null,"budget":0,"genres":[{"id":35,"name":"Comedy"},{"id":878,"name":"Science Fiction"}],"homepage":"","id":2855,"imdb_id":"tt0055137","original_language":"de","original_title":"Der Mann mit dem Objektiv","overview":"A humorous and satirical comedy, which places a man from the year 2222 one day in the (then) present day life in GDR, East Germany under Communist regime. Using a crystal for mind reading he uncovers some improprieties and moral weaknesses in the \"Beautiful future\" professed by VEB (\"Volkseigener Betrieb\" - \"State Owned Holdings\").","popularity":0.706,"poster_path":null,"production_companies":[{"id":602,"logo_path":"/pVsXRFbYVDe5BhsATCAh1rt5F0k.png","name":"DEFA","origin_country":"DE"}],"production_countries":[{"iso_3166_1":"DE","name":"Germany"}],"release_date":"1961-10-05","revenue":0,"runtime":80,"spoken_languages":[{"iso_639_1":"de","name":"Deutsch"}],"status":"Released","tagline":"","title":"Der Mann mit dem Objektiv","video":false,"vote_average":5.0,"vote_count":2}