{"adult":false,"backdrop_path":null,"belongs_to_collection":null,"budget":0,"genres":[{"id":99,"name":"Documentary"}],"homepage":"http://www.oprah.com/app/light-girls.html","id":319913,"imdb_id":"tt4330068","original_language":"en","original_title":"Light Girls","overview":"From the creator and director of the critically acclaimed documentary Dark Girls, award-winning filmmaker Bill Duke continues the conversation on colorism with Light Girls. Sharing the untold stories and experiences of lighter-skinned women, Light Girls dives deep into the discussion of skin color, preference, privilege, pain and prejudice. The documentary features interviews with Russell Simmons, Soledad O'Brien, Diahann Carroll, India Arie, Iyanla Vanzant, Michaela Angela Davis, Kym Whitley, Salli Richardson-Whitfield and more.","popularity":0.887,"poster_path":null,"production_companies":[],"production_countries":[],"release_date":"2015-01-19","revenue":0,"runtime":84,"spoken_languages":[{"iso_639_1":"en","name":"English"}],"status":"Released","tagline":"","title":"Light Girls","video":false,"vote_average":0.0,"vote_count":0}