{"adult":false,"backdrop_path":"/pH6tXFobpuxD7J9kVe0YeKWAnMk.jpg","belongs_to_collection":{"id":709204,"name":"Gus Van Sant's Death Trilogy","poster_path":null,"backdrop_path":null},"budget":0,"genres":[{"id":18,"name":"Drama"}],"homepage":"","id":1665,"imdb_id":"tt0403217","original_language":"en","original_title":"Last Days","overview":"The life and struggles of a notorious rock musician seeping into a pit of loneliness whose everyday life involves friends and family seeking financial aid and favors, inspired by rock music legend Kurt Cobain and his final hours.","popularity":8.276,"poster_path":"/btbp47CHXgLhw30kyDoVfNFLB3g.jpg","production_companies":[{"id":7429,"logo_path":"/6in9uMqxXEHx5XgYgkeRBpZ4rPw.png","name":"HBO Films","origin_country":"US"},{"id":11486,"logo_path":null,"name":"Picturehouse Entertainment","origin_country":""},{"id":13507,"logo_path":null,"name":"Pie Films Inc.","origin_country":""}],"production_countries":[{"iso_3166_1":"US","name":"United States of America"}],"release_date":"2005-05-13","revenue":1928985,"runtime":97,"spoken_languages":[{"iso_639_1":"en","name":"English"}],"status":"Released","tagline":"Rock and roll will never die.","title":"Last Days","video":false,"vote_average":5.6,"vote_count":222}