{"adult":false,"backdrop_path":"/78OcTPni2PQNeRNrsX4mawapF4A.jpg","belongs_to_collection":null,"budget":11000000,"genres":[{"id":35,"name":"Comedy"},{"id":10749,"name":"Romance"}],"homepage":"","id":10646,"imdb_id":"tt0246989","original_language":"en","original_title":"Tomcats","overview":"College buddies chip in and promise that the group's last unmarried man will collect a cash pot. Seven years later, the kitty is worth $500,000 -- money Michael needs to pay a gambling debt. Problem is, the only other single guy is a hopeless womanizer!","popularity":9.229,"poster_path":"/LpIAhTgwyh22Y4BhYbEsZv0u9W.jpg","production_companies":[{"id":497,"logo_path":"/pMyhOBd3sCiLzBlmIopdJkcUFtn.png","name":"Revolution Studios","origin_country":"US"},{"id":5,"logo_path":"/71BqEFAF4V3qjjMPCpLuyJFB9A.png","name":"Columbia Pictures","origin_country":"US"}],"production_countries":[{"iso_3166_1":"US","name":"United States of America"}],"release_date":"2001-03-30","revenue":23430766,"runtime":95,"spoken_languages":[{"iso_639_1":"en","name":"English"}],"status":"Released","tagline":"The Last Man Standing Gets The Kitty.","title":"Tomcats","video":false,"vote_average":5.2,"vote_count":145}