{"adult":false,"backdrop_path":null,"belongs_to_collection":null,"budget":0,"genres":[{"id":10402,"name":"Music"}],"homepage":null,"id":2854,"imdb_id":"","original_language":"de","original_title":"Vor dem Konzert","overview":"Before the concert, three scenes from the life of a successful classical cellist, who finds fulfillment and refuge in music. However, as the precarious balance in which he has set up his life suddenly wavered, a roller coaster of emotions becomes a roller coaster of a normal day before a concert.","popularity":0.6,"poster_path":null,"production_companies":[],"production_countries":[],"release_date":"2007-01-01","revenue":0,"runtime":12,"spoken_languages":[{"iso_639_1":"de","name":"Deutsch"}],"status":"Released","tagline":"","title":"Before The Concert","video":false,"vote_average":0.0,"vote_count":0}