{"adult":false,"backdrop_path":"/gtdCmYpubVkkvTQ8rdR9tkixDSj.jpg","belongs_to_collection":null,"budget":30000000,"genres":[{"id":80,"name":"Crime"},{"id":53,"name":"Thriller"}],"homepage":"","id":10223,"imdb_id":"tt0120324","original_language":"en","original_title":"A Simple Plan","overview":"Captivated by the lure of sudden wealth, the quiet rural lives of two brothers erupt into conflicts of greed, paranoia and distrust when over $4 million in cash is discovered at the remote site of a downed small airplane. Their simple plan to retain the money while avoiding detection opens a Pandora's box when the fear of getting caught triggers panicked behavior and leads to virulent consequences.","popularity":9.31,"poster_path":"/qaVX7jWzJjuHxeXWdt6qQhvWTVZ.jpg","production_companies":[{"id":3324,"logo_path":"/16fY7pucCzn7WSOYxOGRHlAayL3.png","name":"BBC","origin_country":"GB"},{"id":4,"logo_path":"/fycMZt242LVjagMByZOLUGbCvv3.png","name":"Paramount","origin_country":"US"}],"production_countries":[{"iso_3166_1":"US","name":"United States of America"}],"release_date":"1998-12-11","revenue":16316273,"runtime":121,"spoken_languages":[{"iso_639_1":"en","name":"English"}],"status":"Released","tagline":"Sometimes good people do evil things.","title":"A Simple Plan","video":false,"vote_average":7.1,"vote_count":451}