{"adult":false,"backdrop_path":null,"belongs_to_collection":null,"budget":0,"genres":[{"id":16,"name":"Animation"},{"id":35,"name":"Comedy"},{"id":80,"name":"Crime"}],"homepage":"","id":10933,"imdb_id":"tt0387162","original_language":"de","original_title":"Derrick - Die Pflicht ruft!","overview":"No overview found.","popularity":0.835,"poster_path":"/7BNpw3wDkY2AYsJ5ewNfWTpOpKE.jpg","production_companies":[{"id":6236,"logo_path":null,"name":"NDF International","origin_country":""},{"id":101,"logo_path":null,"name":"Roxy Film","origin_country":"DE"},{"id":4606,"logo_path":"/otZHbf1HmzLRQsZFSqJXkf8EHz7.png","name":"ZDF","origin_country":"DE"}],"production_countries":[{"iso_3166_1":"DE","name":"Germany"},{"iso_3166_1":"IE","name":"Ireland"}],"release_date":"2004-04-01","revenue":0,"runtime":80,"spoken_languages":[{"iso_639_1":"de","name":"Deutsch"}],"status":"Released","tagline":"Faltenfrei in gefährlicher Mission","title":"Derrick - Die Pflicht ruft!","video":false,"vote_average":4.2,"vote_count":6}