{"adult":false,"backdrop_path":"/wZ6lLplXHvN1krElg3xWCQrMBJq.jpg","belongs_to_collection":null,"budget":15000000,"genres":[{"id":35,"name":"Comedy"},{"id":18,"name":"Drama"},{"id":10749,"name":"Romance"}],"homepage":"","id":10564,"imdb_id":"tt0198021","original_language":"en","original_title":"Where the Heart Is","overview":"Novalee Nation is a 17-year-old Tennessee transient who has to grow up in a hurry when she's left pregnant and abandoned by her boyfriend on a roadside in Sequoyah, Okla., and takes refuge in the friendly aisles of Wal-Mart. In short order, some eccentric, kindly strangers \"adopt\" Novalee and her infant daughter, helping them buck the odds and build a new life.","popularity":11.303,"poster_path":"/2ylEQVilDE1iywh0RlebJmKRGbI.jpg","production_companies":[{"id":32803,"logo_path":null,"name":"Wind Dancer Films","origin_country":""},{"id":25,"logo_path":"/qZCc1lty5FzX30aOCVRBLzaVmcp.png","name":"20th Century Fox","origin_country":"US"}],"production_countries":[{"iso_3166_1":"US","name":"United States of America"}],"release_date":"2000-04-27","revenue":33771174,"runtime":120,"spoken_languages":[{"iso_639_1":"en","name":"English"}],"status":"Released","tagline":"Laughter is harder... Friendship is stronger... Trust is deeper... When it comes from the heart.","title":"Where the Heart Is","video":false,"vote_average":7.0,"vote_count":425}