{"adult":false,"backdrop_path":"/v9ecuONeI9sJBVyoLyypd2QRQlH.jpg","belongs_to_collection":null,"budget":20000000,"genres":[{"id":18,"name":"Drama"}],"homepage":"http://www.sonypictures.com/movies/reignoverme/index.html","id":2355,"imdb_id":"tt0490204","original_language":"en","original_title":"Reign Over Me","overview":"A man who lost his family in the September 11 attack on New York City runs into his old college roommate. Rekindling the friendship is the one thing that appears able to help the man recover from his grief.","popularity":10.215,"poster_path":"/b5EtDvwj2gdG1qMBLijamlLfJLB.jpg","production_companies":[{"id":2608,"logo_path":"/g3YRudXiQzHesQqRXvnhFpMzfkU.png","name":"Happy Madison Productions","origin_country":"US"},{"id":5,"logo_path":"/71BqEFAF4V3qjjMPCpLuyJFB9A.png","name":"Columbia Pictures","origin_country":"US"},{"id":3800,"logo_path":null,"name":"Sunlight Productions","origin_country":""},{"id":7295,"logo_path":"/5MYE96QiE5a5oFhXxFb4y8ILSpw.png","name":"Relativity Media","origin_country":"US"},{"id":11708,"logo_path":null,"name":"Madison 23","origin_country":""}],"production_countries":[{"iso_3166_1":"US","name":"United States of America"}],"release_date":"2007-03-23","revenue":22222308,"runtime":124,"spoken_languages":[{"iso_639_1":"en","name":"English"}],"status":"Released","tagline":"Let in the unexpected.","title":"Reign Over Me","video":false,"vote_average":7.2,"vote_count":661}