{"adult":false,"backdrop_path":"/eQKEwwe55hvp11XRfZMnHDTMZmW.jpg","belongs_to_collection":null,"budget":0,"genres":[{"id":35,"name":"Comedy"},{"id":18,"name":"Drama"},{"id":14,"name":"Fantasy"}],"homepage":"","id":2928,"imdb_id":"tt0117038","original_language":"en","original_title":"Michael","overview":"Tabloid reporters are sent by their editor to investigate after the paper recieves a letter from a woman claiming an angel is living with her.","popularity":8.502,"poster_path":"/oMqCTpOH10ajUn9Y9PlcepeJtb6.jpg","production_companies":[{"id":11462,"logo_path":"/7ZymELJwuWR4k5p0oeZ3d3WAhO3.png","name":"Alphaville Films","origin_country":""},{"id":1765,"logo_path":null,"name":"Turner Pictures","origin_country":"US"},{"id":174,"logo_path":"/IuAlhI9eVC9Z8UQWOIDdWRKSEJ.png","name":"Warner Bros. Pictures","origin_country":"US"}],"production_countries":[{"iso_3166_1":"US","name":"United States of America"}],"release_date":"1996-12-25","revenue":119718203,"runtime":105,"spoken_languages":[{"iso_639_1":"en","name":"English"},{"iso_639_1":"pt","name":"Português"}],"status":"Released","tagline":"He's an angel... Not a saint.","title":"Michael","video":false,"vote_average":5.7,"vote_count":351}