{"adult":false,"backdrop_path":null,"belongs_to_collection":null,"budget":0,"genres":[{"id":53,"name":"Thriller"},{"id":28,"name":"Action"},{"id":9648,"name":"Mystery"}],"homepage":"","id":2318,"imdb_id":"tt0203053","original_language":"en","original_title":"Pilgrim","overview":"A beautiful artist helps an amnesiac piece together his identity and evade a gangster on his trail.","popularity":5.037,"poster_path":"/mvAPLEELgciLjUeUgKFHzBcyFZj.jpg","production_companies":[{"id":1068,"logo_path":null,"name":"Barzo Productions","origin_country":""},{"id":1069,"logo_path":null,"name":"GFT Entertainment","origin_country":""},{"id":1070,"logo_path":null,"name":"Milagro Films","origin_country":""},{"id":1071,"logo_path":null,"name":"Spice Factory","origin_country":""}],"production_countries":[{"iso_3166_1":"CA","name":"Canada"},{"iso_3166_1":"GB","name":"United Kingdom"},{"iso_3166_1":"MX","name":"Mexico"}],"release_date":"2000-03-31","revenue":0,"runtime":97,"spoken_languages":[{"iso_639_1":"en","name":"English"}],"status":"Released","tagline":"","title":"Pilgrim","video":false,"vote_average":7.0,"vote_count":5}