{"adult":false,"backdrop_path":"/vG027Nr32grjLTvlYUq9LQ6Z1qb.jpg","belongs_to_collection":{"id":937,"name":"The Pink Panther (Original) Collection","poster_path":"/xu6gZ0zGUSR8SC2QLKFaUrX2niM.jpg","backdrop_path":"/9Lc4YOIwprqMYNaUkJRRa5unakk.jpg"},"budget":0,"genres":[{"id":35,"name":"Comedy"},{"id":80,"name":"Crime"},{"id":9648,"name":"Mystery"}],"homepage":"","id":1594,"imdb_id":"tt0058586","original_language":"en","original_title":"A Shot in the Dark","overview":"A Shot in the Dark is the second and more successful film from the Pink Panther film series where both animated and real life sequences are mixed. A cult classic from Blake Edwards based on the play L’Idiot by Marcel Achard and Harry Kurnitz.","popularity":9.783,"poster_path":"/gVbAW20oy6MUcWpaBFYAJWDljvg.jpg","production_companies":[{"id":60,"logo_path":"/oJXpAs4I3W46e4dkaOEzCa4yBko.png","name":"United Artists","origin_country":"US"},{"id":219,"logo_path":null,"name":"The Mirisch Company","origin_country":"US"}],"production_countries":[{"iso_3166_1":"GB","name":"United Kingdom"},{"iso_3166_1":"US","name":"United States of America"}],"release_date":"1964-06-23","revenue":12368234,"runtime":102,"spoken_languages":[{"iso_639_1":"fr","name":"Français"},{"iso_639_1":"en","name":"English"}],"status":"Released","tagline":"The picture that gets away with murder","title":"A Shot in the Dark","video":false,"vote_average":7.4,"vote_count":266}